sanskrit_tts/__init__.py
sanskrit_tts/_version.py
sanskrit_tts/base.py
sanskrit_tts/bhashini_tts.py
sanskrit_tts/gcloud_tts.py
sanskrit_tts/util.py
sanskrit_tts-0.0.5.dist-info/LICENSE
sanskrit_tts-0.0.5.dist-info/METADATA
sanskrit_tts-0.0.5.dist-info/WHEEL
sanskrit_tts-0.0.5.dist-info/top_level.txt
sanskrit_tts-0.0.5.dist-info/RECORD
