Metadata-Version: 2.1
Name: sanskrit_tts
Version: 0.0.5
Summary: A simple python library for converting Sanskrit text to speech.
Home-page: https://github.com/avinashvarna/sanskrit_tts
Author: Avinash Varna
Project-URL: Bug Tracker, https://github.com/avinashvarna/sanskrit_tts/issues
Classifier: Programming Language :: Python :: 3
Classifier: License :: OSI Approved :: MIT License
Classifier: Operating System :: OS Independent
Classifier: Development Status :: 3 - Alpha
License-File: LICENSE
